ai_code_guard/__init__.py
ai_code_guard/cli.py
ai_code_guard/models.py
ai_code_guard/reporters.py
ai_code_guard/scanner.py
ai_code_guard/analyzers/__init__.py
ai_code_guard/analyzers/dependencies.py
ai_code_guard/analyzers/prompt_injection.py
ai_code_guard/analyzers/python_ast.py
ai_code_guard/analyzers/secrets.py
ai_code_guard-1.0.0.dist-info/METADATA
ai_code_guard-1.0.0.dist-info/WHEEL
ai_code_guard-1.0.0.dist-info/entry_points.txt
ai_code_guard-1.0.0.dist-info/licenses/LICENSE
ai_code_guard-1.0.0.dist-info/RECORD
