Metadata-Version: 2.4
Name: ai-code-guard
Version: 1.0.0
Summary: Industry-grade security scanner for AI-generated code with AST analysis, taint tracking, and comprehensive vulnerability detection
Project-URL: Homepage, https://github.com/ai-code-guard/ai-code-guard
Project-URL: Documentation, https://github.com/ai-code-guard/ai-code-guard#readme
Project-URL: Repository, https://github.com/ai-code-guard/ai-code-guard
Project-URL: Issues, https://github.com/ai-code-guard/ai-code-guard/issues
Author: AI Code Guard Pro Contributors
License-Expression: MIT
License-File: LICENSE
Keywords: ai-generated-code,devsecops,llm-security,prompt-injection,sast,security,static-analysis,vulnerability-scanner
Classifier: Development Status :: 4 - Beta
Classifier: Environment :: Console
Classifier: Intended Audience :: Developers
Classifier: Intended Audience :: Information Technology
Classifier: License :: OSI Approved :: MIT License
Classifier: Operating System :: OS Independent
Classifier: Programming Language :: Python :: 3
Classifier: Programming Language :: Python :: 3.10
Classifier: Programming Language :: Python :: 3.11
Classifier: Programming Language :: Python :: 3.12
Classifier: Topic :: Security
Classifier: Topic :: Software Development :: Quality Assurance
Classifier: Topic :: Software Development :: Testing
Classifier: Typing :: Typed
Requires-Python: >=3.10
Requires-Dist: click>=8.0.0
Requires-Dist: gitignore-parser>=0.1.0
Requires-Dist: pathspec>=0.11.0
Requires-Dist: pyyaml>=6.0
Requires-Dist: rich>=13.0.0
Requires-Dist: tomli>=2.0.0; python_version < '3.11'
Provides-Extra: dev
Requires-Dist: mypy>=1.0.0; extra == 'dev'
Requires-Dist: pre-commit>=3.0.0; extra == 'dev'
Requires-Dist: pytest-cov>=4.0.0; extra == 'dev'
Requires-Dist: pytest-xdist>=3.0.0; extra == 'dev'
Requires-Dist: pytest>=7.0.0; extra == 'dev'
Requires-Dist: ruff>=0.1.0; extra == 'dev'
Provides-Extra: js
Requires-Dist: esprima>=4.0.0; extra == 'js'
